{
  "meta": {
    "security_bits": 256,
    "aesni": true,
    "pclmulqdq": true,
    "measured_on": "2026-07-23T19:04:56.088945+00:00"
  },
  "cpu_crypto": {
    "aes_gcm": {
      "throughput_curve": [
        [
          1024,
          1.3528
        ],
        [
          4096,
          4.356
        ],
        [
          16384,
          9.3109
        ],
        [
          65536,
          13.0079
        ],
        [
          262144,
          14.1623
        ],
        [
          1048576,
          14.5587
        ],
        [
          4194304,
          14.502
        ]
      ],
      "fixed_latency_us": 0.7569
    },
    "gmac": {
      "throughput_curve": [
        [
          1024,
          1.456
        ],
        [
          4096,
          5.2007
        ],
        [
          16384,
          14.668
        ],
        [
          65536,
          28.272
        ],
        [
          262144,
          36.1727
        ],
        [
          1048576,
          39.1026
        ],
        [
          4194304,
          27.2106
        ]
      ],
      "fixed_latency_us": 0.7033
    }
  },
  "swiotlb": {
    "map_unmap_fixed_us": 0.0188,
    "private_to_shared_gbps": 17.4753,
    "shared_to_private_gbps": 17.6877
  },
  "pcie": {
    "h2d": {
      "bandwidth_curve": [
        [
          4096,
          0.5859
        ],
        [
          65536,
          7.0359
        ],
        [
          262144,
          20.4323
        ],
        [
          1048576,
          38.5058
        ],
        [
          4194304,
          49.7864
        ],
        [
          16777216,
          53.9187
        ]
      ],
      "fixed_latency_us": 6.991
    },
    "d2h": {
      "bandwidth_curve": [
        [
          4096,
          0.5771
        ],
        [
          65536,
          7.8921
        ],
        [
          262144,
          21.9907
        ],
        [
          1048576,
          40.1474
        ],
        [
          4194304,
          50.3075
        ],
        [
          16777216,
          53.9547
        ]
      ],
      "fixed_latency_us": 7.0971
    }
  },
  "gpu_crypto": {
    "mode": "pcie_line_rate",
    "aes_gcm_gbps": null,
    "gmac_gbps": null
  }
}